Metadata-Version: 1.0
Name: fever-scorer
Version: 2.0.39
Summary: Fact Extraction and VERification scorer
Home-page: https://jamesthorne.co.uk
Author: James Thorne
Author-email: james@jamesthorne.co.uk
License: Type license() to see the full license text
Platform: UNKNOWN
